odoo/addons/account_move_line_menu/README.rst
odoo/addons/account_move_line_menu/__init__.py
odoo/addons/account_move_line_menu/__manifest__.py
odoo/addons/account_move_line_menu/i18n/account_move_line_menu.pot
odoo/addons/account_move_line_menu/i18n/fr.po
odoo/addons/account_move_line_menu/i18n/fr_FR.po
odoo/addons/account_move_line_menu/i18n/hr.po
odoo/addons/account_move_line_menu/readme/CONTRIBUTORS.rst
odoo/addons/account_move_line_menu/readme/DESCRIPTION.rst
odoo/addons/account_move_line_menu/readme/USAGE.rst
odoo/addons/account_move_line_menu/static/description/icon.png
odoo/addons/account_move_line_menu/static/description/index.html
odoo/addons/account_move_line_menu/views/account_menu_views.xml
odoo14_addon_account_move_line_menu-14.0.1.0.1.dev10.dist-info/METADATA
odoo14_addon_account_move_line_menu-14.0.1.0.1.dev10.dist-info/WHEEL
odoo14_addon_account_move_line_menu-14.0.1.0.1.dev10.dist-info/top_level.txt
odoo14_addon_account_move_line_menu-14.0.1.0.1.dev10.dist-info/RECORD
